<?xml version="1.0" encoding="UTF-8"?>
<recurso
	id="PA5_OA_MA_3UNAM_007"
	nivel="Primaria"
	plataforma="HTML 5"
	>
	<titulo><![CDATA[
		Área del triángulo
	]]></titulo>

	<descripcion><![CDATA[
		Este recurso te permitirá determinar y usar la fórmula para calcular el área de cualquier triángulo.
	]]></descripcion>

	<area><![CDATA[
		Matemáticas, geometría, áreas, Forma, espacio y medida, Medida
	]]></area>

	<nivel><![CDATA[
		Básico, primaria
	]]></nivel>

	<tags><![CDATA[
		SEP, UNAM, APRENDEMX, IMATE, LITE, Laboratorio LITE, Área, triángulo, trapecio, figuras planas, base, altura, paralela, perpendicular, corte, traslación, rotación, superficie, igualdad de áreas, fórmula
	]]></tags>

	<vistas>
		meta/icono.png
	</vistas>

	<info>
		http://descartes.matem.unam.mx/recursos/Primaria/AprendeMxUNAM/docs/info.html
	</info>

	<creditos>
		docs/info.html
	</creditos>

	<proyecto id="" ><![CDATA[
		AprendeMx
	]]></proyecto>

</recurso>